awesome_ratelimiter-0.1.0.dist-info/licenses/LICENSE.md
my_ratelimiter/__init__.py
my_ratelimiter/rate_limiter.py
awesome_ratelimiter-0.1.0.dist-info/METADATA
awesome_ratelimiter-0.1.0.dist-info/WHEEL
awesome_ratelimiter-0.1.0.dist-info/top_level.txt
awesome_ratelimiter-0.1.0.dist-info/RECORD
